nmrquant/__init__.py
nmrquant/logger.py
nmrquant/engine/__init__.py
nmrquant/engine/calculator.py
nmrquant/engine/utilities.py
nmrquant/engine/visualizer.py
nmrquant/ui/__init__.py
nmrquant/ui/cli.py
nmrquant/ui/notebook.py
nmrquant-1.2.13.dist-info/LICENSE.txt
nmrquant-1.2.13.dist-info/METADATA
nmrquant-1.2.13.dist-info/WHEEL
nmrquant-1.2.13.dist-info/top_level.txt
nmrquant-1.2.13.dist-info/RECORD
