Metadata-Version: 2.1
Name: nmrquant
Version: 1.2.13
Summary: Quantify metabolites from 1D Proton NMR experiments
Home-page: https://github.com/llegregam/NmrQuant
Author: Loïc Le Grégam
Author-email: legregam@insa-toulouse.fr
Project-URL: Bug Tracker, https://github.com/llegregam/NmrQuant/issues
Classifier: Programming Language :: Python :: 3
Classifier: License :: OSI Approved :: GNU General Public License (GPL)
Classifier: Operating System :: OS Independent
Requires-Python: >=3.8
License-File: LICENSE.txt
Requires-Dist: pandas>=1.3.5
Requires-Dist: numpy>=1.21.6
Requires-Dist: matplotlib>=3.5.2
Requires-Dist: colorcet>=2.0.6
Requires-Dist: ipyfilechooser>=0.4.4
Requires-Dist: ipywidgets>=7.6.3
Requires-Dist: openpyxl>=3.0.7
Requires-Dist: natsort>=7.1.1
Requires-Dist: xlrd>=2.0.1
Requires-Dist: openpyxl>=3.0.9
Requires-Dist: ordered-set>=4.0.2
Requires-Dist: requests>=2.27.1
